trytond/modules/authentication_dummy/__init__.py
trytond/modules/authentication_dummy/setup.py
trytond/modules/authentication_dummy/tryton.cfg
trytond/modules/authentication_dummy/user.py
trytond/modules/authentication_dummy/tests/__init__.py
trytond/modules/authentication_dummy/tests/test_authentication_dummy.py
trytond/modules/authentication_dummy/tests/factories/__init__.py
trytond/modules/authentication_dummy/tests/factories/user.py
trytoncalidae_authentication_dummy-7.2.0.dist-info/LICENSE
trytoncalidae_authentication_dummy-7.2.0.dist-info/METADATA
trytoncalidae_authentication_dummy-7.2.0.dist-info/WHEEL
trytoncalidae_authentication_dummy-7.2.0.dist-info/entry_points.txt
trytoncalidae_authentication_dummy-7.2.0.dist-info/top_level.txt
trytoncalidae_authentication_dummy-7.2.0.dist-info/RECORD
